infsh/__init__.py
infsh/__main__.py
infsh/cli.py
infsh/infsh.py
infsh/templates/inference.py
infsh-0.1.2.dist-info/LICENSE
infsh-0.1.2.dist-info/METADATA
infsh-0.1.2.dist-info/WHEEL
infsh-0.1.2.dist-info/entry_points.txt
infsh-0.1.2.dist-info/top_level.txt
infsh-0.1.2.dist-info/RECORD
