Metadata-Version: 2.2
Name: infsh
Version: 0.1.2
Summary: Helper utilities for building and running inference.sh applications
Author-email: "Inference Shell Inc." <hello@inference.sh>
License: Proprietary
Requires-Python: >=3.8
License-File: LICENSE
Requires-Dist: requests>=2.25.1
Requires-Dist: click>=8.0.0
Requires-Dist: pydantic>=2.0.0
Requires-Dist: pyyaml>=5.4.1
Requires-Dist: pipreqs>=0.5.0
